{
    "boxShadow": "none",
    "iconSVG": "/static/media/icon.f2c34197dbcf03595098986de898928f.svg",
    "topRow": 6,
    "labelWidth": 5,
    "type": "INPUT_WIDGET_V2",
    "animateLoading": true,
    "resetOnSubmit": true,
    "leftColumn": 5,
    "dynamicBindingPathList": [
        {"key": "accentColor"},
        {"key": "borderRadius"}
    ],
    "labelStyle": "",
    "inputType": "TEXT",
    "isDisabled": false,
    "isRequired": false,
    "dynamicHeight": "FIXED",
    "accentColor": "{{appsmith.theme.colors.primaryColor}}",
    "showStepArrows": false,
    "isVisible": true,
    "version": 2,
    "tags": [
        "Suggested",
        "Inputs"
    ],
    "isLoading": false,
    "borderRadius": "{{appsmith.theme.borderRadius.appBorderRadius}}",
    "mobileBottomRow": 13,
    "widgetName": "employeeId",
    "displayName": "Input",
    "searchTags": [
        "form",
        "text input",
        "number",
        "textarea"
    ],
    "bottomRow": 13,
    "parentRowSpace": 10,
    "autoFocus": false,
    "hideCard": false,
    "mobileRightColumn": 25,
    "parentColumnSpace": 3.35546875,
    "labelPosition": "Top",
    "key": "shab4qi1lx",
    "labelTextSize": "0.875rem",
    "isDeprecated": false,
    "rightColumn": 25,
    "widgetId": "u2cg8f3bf6",
    "minWidth": 450,
    "label": "Label",
    "parentId": "wjasazl2oa",
    "labelAlignment": "left",
    "renderMode": "CANVAS",
    "mobileTopRow": 6,
    "responsiveBehavior": "fill",
    "mobileLeftColumn": 5,
    "maxDynamicHeight": 9000,
    "iconAlign": "left",
    "defaultText": "",
    "minDynamicHeight": 4
}